qasdadp/__init__.py
qasdadp/__main__.py
qasdadp-1.0.4.dist-info/LICENSE.txt
qasdadp-1.0.4.dist-info/METADATA
qasdadp-1.0.4.dist-info/WHEEL
qasdadp-1.0.4.dist-info/top_level.txt
qasdadp-1.0.4.dist-info/RECORD
