Metadata-Version: 2.1
Name: qasdadp
Version: 1.0.4
Summary: The qasdad launcher script
Home-page: https://gitlab.com/volkerweissmann/qasdad
Author: Volker Weißmann
Author-email: volker.weissmann@gmx.de
License: UNKNOWN
Platform: UNKNOWN
Classifier: Programming Language :: Python :: 3
Classifier: License :: OSI Approved :: GNU Affero General Public License v3 or later (AGPLv3+)
Classifier: Operating System :: OS Independent
Requires-Dist: qasdad
